indico_patcher/__init__.py
indico_patcher/classes.py
indico_patcher/enums.py
indico_patcher/main.py
indico_patcher/py.typed
indico_patcher/types.py
indico_patcher/util.py
indico_patcher-0.2.1.dist-info/LICENSE
indico_patcher-0.2.1.dist-info/METADATA
indico_patcher-0.2.1.dist-info/WHEEL
indico_patcher-0.2.1.dist-info/RECORD
