Metadata-Version: 2.1
Name: indico-patcher
Version: 0.2.1
Summary: The Swiss Army knife to customize Indico
Home-page: https://github.com/unconventionaldotdev/indico-patcher
License: MIT
Author: Alejandro Avilés
Author-email: ome@unconventional.dev
Requires-Python: >=3.12.2,<3.13
Classifier: Development Status :: 4 - Beta
Classifier: License :: OSI Approved :: MIT License
Classifier: Programming Language :: Python :: 3
Classifier: Topic :: Software Development
Classifier: Topic :: Software Development :: Libraries
Classifier: Topic :: Software Development :: Libraries :: Application Frameworks
Requires-Dist: aenum (>=3.1.15)
Requires-Dist: indico (>=3.3)
Project-URL: Repository, https://github.com/unconventionaldotdev/indico-patcher
